{
  "sections": {
    "title": {
      "type": "sr-only-page-title",
      "settings": {
        "title": "Authors"
      }
    },
    "ff655e28-112c-418d-82f5-b5f0df9d228f": {
      "type": "block-featured-authors",
      "settings": {
        "menu": "",
        "author_1": "autores\/karl-marx",
        "author_2": "autores\/tissot-sylvie",
        "author_3": "",
        "author_4": ""
      }
    },
    "author-list": {
      "type": "main-author-list",
      "settings": {
        "author_grid_featured_menu": "author-index"
      }
    }
  },
  "order": [
    "title",
    "ff655e28-112c-418d-82f5-b5f0df9d228f",
    "author-list"
  ]
}
